{
    "name": "Tiger Fancy Robot",
    "version": "1.0.3",
    "description": "",
    "dependencies": {
        "core": "*",
        "radio": "*",
        "neopixel": "github:kittenbot/pxt-neopixel",
        "Rainbow Sparkle Unicorn": "github:targetarchitecture/pxt-rainbow-sparkle-unicorn#v3.8.2"
    },
    "files": [
        "main.blocks",
        "main.ts",
        "README.md"
    ],
    "testFiles": [],
    "targetVersions": {
        "target": "5.0.12",
        "targetId": "microbit"
    },
    "supportedTargets": [
        "microbit"
    ],
    "preferredEditor": "tsprj",
    "disablesVariants": [
        "mbdal"
    ],
    "binaryonly": true,
    "yotta": {
        "config": {
            "microbit-dal": {
                "bluetooth": {
                    "enabled": 0
                }
            }
        }
    }
}
